{
  "main": {
    "id": "cd5bbe740f97172e",
    "type": "split",
    "children": [
      {
        "id": "093d6a7175c7b759",
        "type": "tabs",
        "children": [
          {
            "id": "a845ea472a5cd6e2",
            "type": "leaf",
            "state": {
              "type": "empty",
              "state": {}
            }
          }
        ]
      }
    ],
    "direction": "vertical"
  },
  "left": {
    "id": "397d0ef7e3d35602",
    "type": "split",
    "children": [
      {
        "id": "fb20d692da40d90c",
        "type": "tabs",
        "children": [
          {
            "id": "93cbd1431b8f6fae",
            "type": "leaf",
            "state": {
              "type": "file-explorer",
              "state": {
                "sortOrder": "alphabetical"
              }
            }
          },
          {
            "id": "facb7e5fa8ba9bd0",
            "type": "leaf",
            "state": {
              "type": "search",
              "state": {
                "query": "final",
                "matchingCase": false,
                "explainSearch": false,
                "collapseAll": false,
                "extraContext": false,
                "sortOrder": "alphabetical"
              }
            }
          },
          {
            "id": "7176f88bf8c811d2",
            "type": "leaf",
            "state": {
              "type": "bookmarks",
              "state": {}
            }
          }
        ]
      }
    ],
    "direction": "horizontal",
    "width": 208.5
  },
  "right": {
    "id": "a25c65a9be484658",
    "type": "split",
    "children": [
      {
        "id": "7a83fb7e154da7b2",
        "type": "tabs",
        "children": [
          {
            "id": "99d33555ecc87372",
            "type": "leaf",
            "state": {
              "type": "backlink",
              "state": {
                "collapseAll": false,
                "extraContext": false,
                "sortOrder": "alphabetical",
                "showSearch": false,
                "searchQuery": "",
                "backlinkCollapsed": false,
                "unlinkedCollapsed": true
              }
            }
          },
          {
            "id": "1713a25a72f856b5",
            "type": "leaf",
            "state": {
              "type": "outgoing-link",
              "state": {
                "linksCollapsed": false,
                "unlinkedCollapsed": true
              }
            }
          },
          {
            "id": "7b636b378a86417e",
            "type": "leaf",
            "state": {
              "type": "tag",
              "state": {
                "sortOrder": "frequency",
                "useHierarchy": true
              }
            }
          },
          {
            "id": "dfeec98fc806c576",
            "type": "leaf",
            "state": {
              "type": "outline",
              "state": {}
            }
          },
          {
            "id": "2a59fdfdf498d522",
            "type": "leaf",
            "state": {
              "type": "calendar",
              "state": {}
            }
          }
        ]
      }
    ],
    "direction": "horizontal",
    "width": 300,
    "collapsed": true
  },
  "left-ribbon": {
    "hiddenItems": {
      "switcher:Open quick switcher": false,
      "graph:Open graph view": false,
      "canvas:Create new canvas": false,
      "daily-notes:Open today's daily note": false,
      "templates:Insert template": false,
      "command-palette:Open command palette": false,
      "publish:Publish changes...": false,
      "obsidian-excalidraw-plugin:Create new drawing": false,
      "obsidian-advanced-slides:Show Slide Preview": false
    }
  },
  "active": "a845ea472a5cd6e2",
  "lastOpenFiles": [
    "Courses/Calculus/Sections/4.8.1 Derivatives - Optimization 1.md",
    "Courses/Calculus/Calculus.canvas",
    "Courses/Calculus/CheatSheets/Calculus_Cheat_Sheet_All.pdf",
    "Courses/Calculus/Sections/2.5 Limits - Computing Limits - Practice.md",
    "Courses/Derivatives.md",
    "Courses/Cheat sheets.md",
    "Courses/Trigonometry.md",
    "Screenshot 2024-03-26 at 6.01.00 AM.png",
    "Courses/Calculus/Sections/2.5 Limits - Computing Limits - Assignment.md",
    "Courses/Calculus/Sections/4.8 Derivatives - Optimization.md",
    "Courses/Calculus/Sections/4.6 Derivatives - The Shape Of A Graph, Part II.md",
    "Courses/Calculus/Sections/4.7 Derivatives - The Mean Value Theorem.md",
    "Concepts/Calculus/Second Derivatives.md",
    "JSO.md",
    "Courses/Calculus/Sections/4.14 Derivatives - Business Applications.md",
    "Concepts/Calculus/7 Rules of Differentiation.md",
    "Optimization Steps.png",
    "Courses/DSA/Trie.md",
    "Courses/DSA/Tree.md",
    "Courses/DSA/Stack.md",
    "Courses/DSA/Matrix.md",
    "Courses/DSA/Queue.md",
    "Courses/DSA/Linked List.md",
    "Courses/DSA/Heap.md",
    "Courses/DSA/HashSet.md",
    "Courses/DSA/HashMap.md",
    "Courses/DSA/Graph.md",
    "Courses/DSA/Array.md",
    "Courses/Analytically.md",
    "Courses/DSA",
    "IMG_0011.jpg",
    "IMG_0010.jpg",
    "IMG_0009.jpg",
    "IMG_0008.jpg",
    "Functions - Piecewise, Mostly continuous, Continuous.png",
    "test.py",
    "2..png",
    "1..png",
    "Pasted image 20240322054630.png",
    "Courses/Calculus/Sections",
    "Docs/latex-example.pdf",
    "Courses/Obsidian",
    "Courses/Calculus/CheatSheets/Common_Derivatives_Integrals.pdf",
    "Courses/Calculus/CheatSheets/Trig_Cheat_Sheet.pdf",
    "Courses/Calculus/6.3 Integrals - Volumes of Solids of Revolution",
    "Courses/Calculus/3.11 Derivatives - Related Rates",
    "Untitled 1.canvas",
    "Overview.canvas"
  ]
}